pysharek/__init__.py
pysharek/__main__.py
pysharek/__version__.py
pysharek/args.py
pysharek/crypto.py
pysharek/hashes_work.py
pysharek/main.py
pysharek/net.py
pysharek/sup.py
pysharek/vs_man_on_middle.py
pysharek/work.py
pysharek-0.12.0.dist-info/LICENSE
pysharek-0.12.0.dist-info/METADATA
pysharek-0.12.0.dist-info/WHEEL
pysharek-0.12.0.dist-info/entry_points.txt
pysharek-0.12.0.dist-info/top_level.txt
pysharek-0.12.0.dist-info/RECORD
