Metadata-Version: 2.1
Name: pysharek
Version: 0.12.0
Summary: Share file with encryption and hash checking
Author-email: The220th <author@example.com>
Project-URL: Homepage, https://github.com/The220th/pysharek
Project-URL: Issues, https://github.com/The220th/pysharek/issues
Classifier: Programming Language :: Python :: 3
Classifier: License :: OSI Approved :: MIT License
Classifier: Operating System :: OS Independent
Requires-Python: >=3.7
License-File: LICENSE
Requires-Dist: cryptography
Requires-Dist: argparse
Requires-Dist: alive-progress
